zira/__init__.py
zira/logger.py
zira/sync.py
zira-1.0.4.dist-info/LICENSE
zira-1.0.4.dist-info/METADATA
zira-1.0.4.dist-info/WHEEL
zira-1.0.4.dist-info/top_level.txt
zira-1.0.4.dist-info/RECORD
