Metadata-Version: 2.1
Name: zira
Version: 1.0.4
Summary: Async logging system with local caching and syncing system
Home-page: https://github.com/ShayanSadeghi/zira
Author: Shayan Sadeghi
Author-email: ShayanSadeghi1996@gmail.com
Keywords: log,event-logger,logger,monitor
Classifier: Programming Language :: Python :: 3
Classifier: License :: OSI Approved :: Apache Software License
Classifier: Operating System :: OS Independent
Requires-Python: >=3.6
License-File: LICENSE
Requires-Dist: motor>=3.6.0
Requires-Dist: python-dotenv>=1.0.1
